{
  "props": {
    "data": [
      {
        "id": 1,
        "name": "Pascale Persicke",
        "country": "Indonesia",
        "email": "ppersicke0@arstechnica.com",
        "gender": "Male"
      },
      {
        "id": 2,
        "name": "Beth Tremmil",
        "country": "Indonesia",
        "email": "btremmil1@multiply.com",
        "gender": "Female"
      },
      {
        "id": 3,
        "name": "Leoline Shambrooke",
        "country": "China",
        "email": "lshambrooke2@ibm.com",
        "gender": "Female"
      },
      {
        "id": 4,
        "name": "Domenic Kleinert",
        "country": "Albania",
        "email": "dkleinert3@hubpages.com",
        "gender": "Male"
      },
      {
        "id": 5,
        "name": "Charmane Crommett",
        "country": "China",
        "email": "ccrommett4@nih.gov",
        "gender": "Female"
      },
      {
        "id": 6,
        "name": "Kienan Proctor",
        "country": "China",
        "email": "kproctor5@msn.com",
        "gender": "Male"
      },
      {
        "id": 7,
        "name": "Dorian Gurrado",
        "country": "Sweden",
        "email": "dgurrado6@xrea.com",
        "gender": "Female"
      },
      {
        "id": 8,
        "name": "Marilyn MacNeice",
        "country": "China",
        "email": "mmacneice7@prnewswire.com",
        "gender": "Female"
      },
      {
        "id": 9,
        "name": "Upton Karmel",
        "country": "Indonesia",
        "email": "ukarmel8@spiegel.de",
        "gender": "Male"
      },
      {
        "id": 10,
        "name": "Rhett Jellard",
        "country": "Indonesia",
        "email": "rjellard9@vk.com",
        "gender": "Male"
      }
    ]
  }
}
